cs/gvutils.py
cs.gvutils-20230816.dist-info/METADATA
cs.gvutils-20230816.dist-info/WHEEL
cs.gvutils-20230816.dist-info/top_level.txt
cs.gvutils-20230816.dist-info/RECORD
